lsdb_crossmatch/__init__.py
lsdb_crossmatch/_version.py
lsdb_crossmatch/example_module.py
lsdb_crossmatch/mag_difference_crossmatch.py
lsdb_crossmatch-0.1.0.dist-info/licenses/LICENSE
lsdb_crossmatch-0.1.0.dist-info/METADATA
lsdb_crossmatch-0.1.0.dist-info/WHEEL
lsdb_crossmatch-0.1.0.dist-info/top_level.txt
lsdb_crossmatch-0.1.0.dist-info/RECORD
