Metadata-Version: 2.4
Name: lsdb-crossmatch
Version: 0.1.0
Author-email: LINCC Frameworks <lincc-frameworks-team@lists.lsst.org>
License: BSD 3-Clause License
Project-URL: Source Code, https://github.com/astronomy-commons/lsdb-crossmatch
Classifier: Development Status :: 4 - Beta
Classifier: License :: OSI Approved :: BSD License
Classifier: Intended Audience :: Developers
Classifier: Intended Audience :: Science/Research
Classifier: Operating System :: OS Independent
Classifier: Programming Language :: Python
Requires-Python: >=3.10
License-File: LICENSE
Requires-Dist: lsdb>=0.6.0
Provides-Extra: dev
Requires-Dist: black; extra == "dev"
Requires-Dist: jupyter; extra == "dev"
Requires-Dist: pre-commit; extra == "dev"
Requires-Dist: pylint; extra == "dev"
Requires-Dist: pytest; extra == "dev"
Requires-Dist: pytest-cov; extra == "dev"
Dynamic: license-file
